examples/primer_selection_example.py
primavera/Primer.py
primavera/PrimerSelector.py
primavera/ReadReferenceMatches.py
primavera/SequencingReportGenerator.py
primavera/__init__.py
primavera/biotools.py
primavera/sequencing_simulation.py
primavera/tools.py
primavera/version.py
primavera-0.1.14.dist-info/licenses/LICENCE.txt
tests/test_primer_selection.py
primavera-0.1.14.dist-info/METADATA
primavera-0.1.14.dist-info/WHEEL
primavera-0.1.14.dist-info/top_level.txt
primavera-0.1.14.dist-info/RECORD
