Metadata-Version: 2.4
Name: primavera
Version: 0.1.14
Summary: Primer selection + data analysis for DNA assembly validation.
Author: Zulko
License-Expression: MIT
Project-URL: Homepage, https://github.com/Edinburgh-Genome-Foundry/Primavera
Keywords: DNA,assembly,sequencing,primer,design
License-File: LICENCE.txt
Requires-Dist: numpy
Requires-Dist: Biopython
Requires-Dist: proglog
Requires-Dist: flametree
Requires-Dist: pandas
Requires-Dist: dna_features_viewer
Requires-Dist: dnachisel
Dynamic: license-file
